README.md
setup.py
CantrelleJouisseMamannVF.egg-info/PKG-INFO
CantrelleJouisseMamannVF.egg-info/SOURCES.txt
CantrelleJouisseMamannVF.egg-info/dependency_links.txt
CantrelleJouisseMamannVF.egg-info/top_level.txt
philcantrel/Data_viz_a_packager_propre.py
philcantrel/__init__.py
philcantrel/module_carte.py
tests_package/Test_unitaires.py
tests_package/__init__.py
tests_package/test_graphe_version_py.py